ats_coverage/__init__.py
ats_coverage/py.typed
ats_coverage/conf/ats_coverage.cfg
ats_coverage/conf/ats_coverage.logo
ats_coverage/conf/ats_coverage_util.cfg
ats_coverage/log/ats_coverage.log
ats_coverage/pro/__init__.py
ats_coverage-1.0.5.dist-info/licenses/LICENSE
usr/local/bin/ats_coverage_run.py
ats_coverage-1.0.5.dist-info/METADATA
ats_coverage-1.0.5.dist-info/WHEEL
ats_coverage-1.0.5.dist-info/top_level.txt
ats_coverage-1.0.5.dist-info/RECORD
