Metadata-Version: 2.4
Name: ats_coverage
Version: 1.0.5
Summary: Python code coverage automation
Home-page: https://vroncevic.github.io/ats_coverage
Author: Vladimir Roncevic
Author-email: elektron.ronca@gmail.com
License: GPL-3.0-or-later
Keywords: code,coverage,automation
Platform: any
Classifier: Programming Language :: Python :: 3.10
Classifier: Programming Language :: Python :: 3.11
Classifier: Programming Language :: Python :: 3.12
License-File: LICENSE
Requires-Dist: ats_utilities
Requires-Dist: coverage
Dynamic: author
Dynamic: author-email
Dynamic: classifier
Dynamic: description
Dynamic: description-content-type
Dynamic: home-page
Dynamic: keywords
Dynamic: license
Dynamic: license-file
Dynamic: platform
Dynamic: requires-dist
Dynamic: summary
